flake8_broken_line.py
flake8_broken_line-0.1.1.dist-info/entry_points.txt
flake8_broken_line-0.1.1.dist-info/LICENSE
flake8_broken_line-0.1.1.dist-info/WHEEL
flake8_broken_line-0.1.1.dist-info/METADATA
flake8_broken_line-0.1.1.dist-info/RECORD
